[
    {
        "time": "01:45",
        "tournament": "AFC Champions League",
        "eventTitle": "Melbourne City vs. Sanfrecce Hiroshima",
        "streams": [
            {
                "url": "aHR0cHM6Ly92b29kYy5jb20vZW1iZWQvODU4MThiOTk5Yzg3YTE4Yjg0N2E4NTk1OWY4ZTk4ODUuaHRtbA==",
                "optionText": "TV"
            }
        ]
    },
    {
        "time": "04:00",
        "tournament": "AFC Champions League",
        "eventTitle": "Gangwon vs. Shanghai Shenhua",
        "streams": [
            {
                "url": "aHR0cHM6Ly92b29kYy5jb20vZW1iZWQvODU4MThiOTk5Yzg4OWY4Yzg0N2E4NTlhOWM4Nzk4ODkuaHRtbA==",
                "optionText": "TV"
            }
        ]
    },
    {
        "time": "04:00",
        "tournament": "AFC Champions League",
        "eventTitle": "Machida Zelvia vs. FC Seoul",
        "streams": [
            {
                "url": "aHR0cHM6Ly92b29kYy5jb20vZW1iZWQvODU4MThiOTk5Yzg4OWY4Yzg0N2E4NTlhOWM4ODk4OGEuaHRtbA==",
                "optionText": "TV"
            }
        ]
    },
    {
        "time": "04:00",
        "tournament": "UEFA Youth League",
        "eventTitle": "Athletic Bilbao U19 vs. Arsenal U19",
        "streams": [
            {
                "url": "aHR0cHM6Ly92b29kYy5jb20vZW1iZWQvODU4MThiOTk5Yzg4OWY4Yzg0N2E4NTlhOWM4OTk4OGIuaHRtbA==",
                "optionText": "TV"
            }
        ]
    },
    {
        "time": "04:00",
        "tournament": "UEFA Youth League",
        "eventTitle": "Benfica U19 vs. Qarabag U19",
        "streams": [
            {
                "url": "aHR0cHM6Ly92b29kYy5jb20vZW1iZWQvODU4MThiOTk5Yzg4OWY4Yzg0N2E4NTlhOWM4YTk4OGMuaHRtbA==",
                "optionText": "TV"
            }
        ]
    },
    {
        "time": "04:30",
        "tournament": "Turkish Cup",
        "eventTitle": "Agri 1970 vs. Batman Petrolspor",
        "streams": [
            {
                "url": "aHR0cHM6Ly92b29kYy5jb20vZW1iZWQvODU4MThiOTk5Yzg4YTE4YTg0N2E4NTlhOWM4Yzk4ODU4NC5odG1s",
                "optionText": "TV"
            }
        ]
    },
    {
        "time": "06:00",
        "tournament": "UEFA Youth League",
        "eventTitle": "Juventus U19 vs. Dortmund U19",
        "streams": [
            {
                "url": "aHR0cHM6Ly92b29kYy5jb20vZW1iZWQvODU4MThiOTk5Yzg5OWQ4NDg0N2E4NTlhOWM4YTk4ODU4NS5odG1s",
                "optionText": "TV"
            }
        ]
    },
    {
        "time": "06:15",
        "tournament": "AFC Champions League",
        "eventTitle": "Buriram vs. Johor DT",
        "streams": [
            {
                "url": "aHR0cHM6Ly92b29kYy5jb20vZW1iZWQvODU4MThiOTk5Yzg5OWQ4ZDg0N2E4NTlhOWM4Zjk4ODU4Ni5odG1s",
                "optionText": "TV"
            }
        ]
    },
    {
        "time": "06:30",
        "tournament": "Turkish Cup",
        "eventTitle": "Kirikkale FK vs. Manisa FK",
        "streams": [
            {
                "url": "aHR0cHM6Ly92b29kYy5jb20vZW1iZWQvODU4MThiOTk5Yzg5OWU4Yzg0N2E4NTlhOWM4Yzk4ODU4Ny5odG1s",
                "optionText": "TV"
            }
        ]
    },
    {
        "time": "07:30",
        "tournament": "Russian Cup",
        "eventTitle": "Orenburg vs. Rubin Kazan",
        "streams": [
            {
                "url": "aHR0cHM6Ly92b29kYy5jb20vZW1iZWQvODU4MThiOTk5Yzg5YTI4ODg0N2E4NTlhOWQ4Nzk4ODU4OS5odG1s",
                "optionText": "TV"
            }
        ]
    },
    {
        "time": "07:45",
        "tournament": "AFC Champions League 2",
        "eventTitle": "Mohun Bagan vs. Ahal",
        "streams": [
            {
                "url": "aHR0cHM6Ly92b29kYy5jb20vZW1iZWQvODU4MThiOTk5YzhhOTk4Nzg0N2E4NTlhOWQ4OTk4ODU4Yi5odG1s",
                "optionText": "TV"
            }
        ]
    },
    {
        "time": "08:00",
        "tournament": "Croatian Cup",
        "eventTitle": "Neretva vs. Istra 1961",
        "streams": [
            {
                "url": "aHR0cHM6Ly92b29kYy5jb20vZW1iZWQvODU4MThiOTk5YzhhOWE4Njg0N2E4NTlhOWQ4YTk4ODU4ZC5odG1s",
                "optionText": "TV"
            }
        ]
    },
    {
        "time": "09:00",
        "tournament": "Turkish Cup",
        "eventTitle": "Tire 2021 FK vs. Bodrumspor",
        "streams": [
            {
                "url": "aHR0cHM6Ly92b29kYy5jb20vZW1iZWQvODU4MThiOTk5YzhhOWQ4Yzg0N2E4NTk3OWM4Yjk4ODc4OC5odG1s",
                "optionText": "TV"
            }
        ]
    },
    {
        "time": "09:30",
        "tournament": "Lithuanian Cup",
        "eventTitle": "Suduva vs. FK Panevezys",
        "streams": [
            {
                "url": "aHR0cHM6Ly92b29kYy5jb20vZW1iZWQvODU4MThiOTk5YzhhOWY4YTg0N2E4NTk3OWM4ZDk4ODg4Ny5odG1s",
                "optionText": "TV"
            }
        ]
    },
    {
        "time": "09:45",
        "tournament": "Russian Cup",
        "eventTitle": "Akron Togliatti vs. Lokomotiv Moscow",
        "streams": [
            {
                "url": "aHR0cHM6Ly92b29kYy5jb20vZW1iZWQvODU4MThiOTk5YzhhYTA4OTg0N2E4NTk3OWQ4Yzk4ODg4OC5odG1s",
                "optionText": "TV"
            }
        ]
    },
    {
        "time": "10:00",
        "tournament": "AFC Champions League",
        "eventTitle": "Shabab Al-Ahli Dubai vs. Tractor",
        "streams": [
            {
                "url": "aHR0cHM6Ly92b29kYy5jb20vZW1iZWQvODU4MThiOTk5YzhhYTE4ODg0N2E4NTk3OWQ4ZTk4ODk4OC5odG1s",
                "optionText": "TV"
            }
        ]
    },
    {
        "time": "10:00",
        "tournament": "OFB Cup",
        "eventTitle": "Reichenau vs. Wolfsberger AC",
        "streams": [
            {
                "url": "aHR0cHM6Ly92b29kYy5jb20vZW1iZWQvODU4MThiOTk5YzhhYTE4ODg0N2E4NTk3OWQ4Zjk4ODk4OS5odG1s",
                "optionText": "TV"
            }
        ]
    },
    {
        "time": "10:30",
        "tournament": "Israel Ligat haAl",
        "eventTitle": "Hapoel Petah Tikva vs. Maccabi Tel Aviv",
        "streams": [
            {
                "url": "aHR0cHM6Ly92b29kYy5jb20vZW1iZWQvODU4MThiOTk5YzhiOTk4Njg0N2E4NTk3OWU4ZTk4OGE4NS5odG1s",
                "optionText": "TV"
            }
        ]
    },
    {
        "time": "10:45",
        "tournament": "UEFA Champions League",
        "eventTitle": "Athletic Bilbao vs. Arsenal",
        "streams": [
            {
                "url": "aHR0cHM6Ly92b29kYy5jb20vZW1iZWQvODU4MThiOTk5YzhiOWE4NTg0N2E4NTk3OWY4Yzk4OGE4OC5odG1s",
                "optionText": "TV"
            },
            {
                "url": "aHR0cHM6Ly92b29kYy5jb20vZW1iZWQvODU4MThiOTk5YzhiOWE4NTg0N2E4NTk3OWY4ZDk4OGE4OS5odG1s",
                "optionText": "TV"
            },
            {
                "url": "aHR0cHM6Ly92b29kYy5jb20vZW1iZWQvODU4MThiOTk5YzhiOWE4NTg0N2E4NTk3OWY4ZTk4OGE4YS5odG1s",
                "optionText": "TV"
            },
            {
                "url": "aHR0cHM6Ly92b29kYy5jb20vZW1iZWQvODU4MThiOTk5YzhiOWE4NTg0N2E4NTk3OWY4Zjk4OGE4Yi5odG1s",
                "optionText": "TV"
            },
            {
                "url": "aHR0cHM6Ly92b29kYy5jb20vZW1iZWQvODU4MThiOTk5YzhiOWE4NTg0N2E4NTk3OWY5MDk4OGE4Yy5odG1s",
                "optionText": "TV"
            }
        ]
    },
    {
        "time": "10:45",
        "tournament": "UEFA Champions League",
        "eventTitle": "PSV vs. Royale Union SG",
        "streams": [
            {
                "url": "aHR0cHM6Ly92b29kYy5jb20vZW1iZWQvODU4MThiOTk5YzhiOWE4NTg0N2E4NTk3YTA4Nzk4OGE4ZC5odG1s",
                "optionText": "TV"
            },
            {
                "url": "aHR0cHM6Ly92b29kYy5jb20vZW1iZWQvODU4MThiOTk5YzhiOWE4NTg0N2E4NTk3YTA4ODk4OGI4NC5odG1s",
                "optionText": "TV"
            },
            {
                "url": "aHR0cHM6Ly92b29kYy5jb20vZW1iZWQvODU4MThiOTk5YzhiOWE4NTg0N2E4NTk3YTA4OTk4OGI4NS5odG1s",
                "optionText": "TV"
            },
            {
                "url": "aHR0cHM6Ly92b29kYy5jb20vZW1iZWQvODU4MThiOTk5YzhiOWE4NTg0N2E4NTk3YTA4YTk4OGI4Ni5odG1s",
                "optionText": "TV"
            }
        ]
    },
    {
        "time": "10:45",
        "tournament": "Malta",
        "eventTitle": "Floriana vs. Valletta",
        "streams": [
            {
                "url": "aHR0cHM6Ly92b29kYy5jb20vZW1iZWQvODU4MThiOTk5YzhiOWE4NTg0N2E4NTk3YTA4Yjk4OGI4Ny5odG1s",
                "optionText": "TV"
            }
        ]
    },
    {
        "time": "10:45",
        "tournament": "Malta",
        "eventTitle": "Zabbar vs. Hamrun",
        "streams": [
            {
                "url": "aHR0cHM6Ly92b29kYy5jb20vZW1iZWQvODU4MThiOTk5YzhiOWE4NTg0N2E4NTk3YTA4Yzk4OGI4OC5odG1s",
                "optionText": "TV"
            }
        ]
    },
    {
        "time": "11:00",
        "tournament": "Bundesliga 3",
        "eventTitle": "Saarbrucken vs. Ulm",
        "streams": [
            {
                "url": "aHR0cHM6Ly92b29kYy5jb20vZW1iZWQvODU4MThiOTk5YzhiOWI4NDg0N2E4NTk3YTA4ZDk4OGM4OS5odG1s",
                "optionText": "TV"
            }
        ]
    },
    {
        "time": "11:00",
        "tournament": "Bundesliga 3",
        "eventTitle": "Schweinfurt vs. Duisburg",
        "streams": [
            {
                "url": "aHR0cHM6Ly92b29kYy5jb20vZW1iZWQvODU4MThiOTk5YzhiOWI4NDg0N2E4NTk3YTA4ZTk4OGM4YS5odG1s",
                "optionText": "TV"
            }
        ]
    },
    {
        "time": "11:00",
        "tournament": "Bundesliga 3",
        "eventTitle": "Verl vs. Alemannia Aachen",
        "streams": [
            {
                "url": "aHR0cHM6Ly92b29kYy5jb20vZW1iZWQvODU4MThiOTk5YzhiOWI4NDg0N2E4NTk3YTA4Zjk4OGM4Yi5odG1s",
                "optionText": "TV"
            }
        ]
    },
    {
        "time": "11:00",
        "tournament": "Bundesliga 3",
        "eventTitle": "Viktoria Koln vs. Hoffenheim II",
        "streams": [
            {
                "url": "aHR0cHM6Ly92b29kYy5jb20vZW1iZWQvODU4MThiOTk5YzhiOWI4NDg0N2E4NTk3YTA5MDk4OGM4Yy5odG1s",
                "optionText": "TV"
            }
        ]
    },
    {
        "time": "11:00",
        "tournament": "Bundesliga 3",
        "eventTitle": "Wehen vs. Regensburg",
        "streams": [
            {
                "url": "aHR0cHM6Ly92b29kYy5jb20vZW1iZWQvODU4MThiOTk5YzhiOWI4NDg0N2E4NTk3YTE4Nzk4OGM4ZC5odG1s",
                "optionText": "TV"
            }
        ]
    },
    {
        "time": "11:00",
        "tournament": "Ligue 2",
        "eventTitle": "Boulogne vs. Bastia",
        "streams": [
            {
                "url": "aHR0cHM6Ly92b29kYy5jb20vZW1iZWQvODU4MThiOTk5YzhiOWI4NDg0N2E4NTk3YTE4ODk4OGQ4NC5odG1s",
                "optionText": "TV"
            }
        ]
    },
    {
        "time": "11:00",
        "tournament": "Superettan",
        "eventTitle": "Helsingborg vs. Landskrona",
        "streams": [
            {
                "url": "aHR0cHM6Ly92b29kYy5jb20vZW1iZWQvODU4MThiOTk5YzhiOWI4NDg0N2E4NTk3YTE4OTk4OGQ4NS5odG1s",
                "optionText": "TV"
            }
        ]
    },
    {
        "time": "11:30",
        "tournament": "Turkish Cup",
        "eventTitle": "Hatayspor vs. Erciyes 38",
        "streams": [
            {
                "url": "aHR0cHM6Ly92b29kYy5jb20vZW1iZWQvODU4MThiOTk5YzhiOWM4Yzg0N2E4NTk3YTI4Yjk4OGQ4OC5odG1s",
                "optionText": "TV"
            }
        ]
    },
    {
        "time": "11:45",
        "tournament": "Russian Cup",
        "eventTitle": "Pari NN vs. Dynamo Makhachkala",
        "streams": [
            {
                "url": "aHR0cHM6Ly92b29kYy5jb20vZW1iZWQvODU4MThiOTk5YzhiOWQ4Yjg0N2E4NTk3YTI4Yzk4ODU4NDdjLmh0bWw=",
                "optionText": "TV"
            }
        ]
    },
    {
        "time": "12:00",
        "tournament": "Eerste Divisie",
        "eventTitle": "FC Oss vs. VVV Venlo",
        "streams": [
            {
                "url": "aHR0cHM6Ly92b29kYy5jb20vZW1iZWQvODU4MThiOTk5YzhiOWU4YTg0N2E4NTk3YTM4YTk4ODU4NDgzLmh0bWw=",
                "optionText": "TV"
            }
        ]
    },
    {
        "time": "12:00",
        "tournament": "Eerste Divisie",
        "eventTitle": "Helmond vs. Jong Utrecht",
        "streams": [
            {
                "url": "aHR0cHM6Ly92b29kYy5jb20vZW1iZWQvODU4MThiOTk5YzhiOWU4YTg0N2E4NTk3YTM4Yjk4ODU4NTdhLmh0bWw=",
                "optionText": "TV"
            }
        ]
    },
    {
        "time": "12:00",
        "tournament": "Eerste Divisie",
        "eventTitle": "MVV Maastricht vs. Den Bosch",
        "streams": [
            {
                "url": "aHR0cHM6Ly92b29kYy5jb20vZW1iZWQvODU4MThiOTk5YzhiOWU4YTg0N2E4NTk3YTM4Yzk4ODU4NTdiLmh0bWw=",
                "optionText": "TV"
            }
        ]
    },
    {
        "time": "12:00",
        "tournament": "Eerste Divisie",
        "eventTitle": "RKC Waalwijk vs. Vitesse",
        "streams": [
            {
                "url": "aHR0cHM6Ly92b29kYy5jb20vZW1iZWQvODU4MThiOTk5YzhiOWU4YTg0N2E4NTk3YTM4ZDk4ODU4NTdjLmh0bWw=",
                "optionText": "TV"
            }
        ]
    },
    {
        "time": "12:00",
        "tournament": "EFL Trophy",
        "eventTitle": "Blackpool vs. Barrow",
        "streams": [
            {
                "url": "aHR0cHM6Ly92b29kYy5jb20vZW1iZWQvODU4MThiOTk5YzhiOWU4YTg0N2E4NTk3YTM4ZTk4ODU4NDgxLmh0bWw=",
                "optionText": "TV"
            }
        ]
    },
    {
        "time": "12:00",
        "tournament": "EFL Trophy",
        "eventTitle": "Exeter City vs. Cardiff City",
        "streams": [
            {
                "url": "aHR0cHM6Ly92b29kYy5jb20vZW1iZWQvODU4MThiOTk5YzhiOWU4YTg0N2E4NTk3YTM4Zjk4ODU4NDgyLmh0bWw=",
                "optionText": "TV"
            }
        ]
    },
    {
        "time": "12:15",
        "tournament": "AFC Champions League",
        "eventTitle": "Al Hilal vs. Al-Duhail",
        "streams": [
            {
                "url": "aHR0cHM6Ly92b29kYy5jb20vZW1iZWQvODU4MThiOTk5YzhiOWY4OTg0N2E4NTk3YTM5MDk4ODU4NTdlLmh0bWw=",
                "optionText": "TV"
            }
        ]
    },
    {
        "time": "12:15",
        "tournament": "AFC Champions League 2",
        "eventTitle": "Al Hussein vs. Sepahan",
        "streams": [
            {
                "url": "aHR0cHM6Ly92b29kYy5jb20vZW1iZWQvODU4MThiOTk5YzhiOWY4OTg0N2E4NTk3YTQ4Nzk4ODU4NTdkLmh0bWw=",
                "optionText": "TV"
            }
        ]
    },
    {
        "time": "12:45",
        "tournament": "EFL Cup",
        "eventTitle": "Sheffield Wednesday vs. Grimsby",
        "streams": [
            {
                "url": "aHR0cHM6Ly92b29kYy5jb20vZW1iZWQvODU4MThiOTk5YzhiYTE4Nzg0N2E4NTk3YTQ4OTk4ODU4NTgwLmh0bWw=",
                "optionText": "TV"
            }
        ]
    },
    {
        "time": "13:00",
        "tournament": "UEFA Champions League",
        "eventTitle": "Simulcast",
        "streams": [
            {
                "url": "aHR0cHM6Ly92b29kYy5jb20vZW1iZWQvODU4MThiOTk5YzhiYTI4Njg0N2E4NTk4OWM4Nzk4ODU4NjgzLmh0bWw=",
                "optionText": "TV"
            },
            {
                "url": "aHR0cHM6Ly92b29kYy5jb20vZW1iZWQvODU4MThiOTk5YzhiYTI4Njg0N2E4NTk5YTE4Nzk4ODY4NTdjLmh0bWw=",
                "optionText": "TV"
            }
        ]
    },
    {
        "time": "13:00",
        "tournament": "UEFA Champions League",
        "eventTitle": "Benfica vs. Qarabag",
        "streams": [
            {
                "url": "aHR0cHM6Ly92b29kYy5jb20vZW1iZWQvODU4MThiOTk5YzhiYTI4Njg0N2E4NTk4OWM4ODk4ODU4NTgxLmh0bWw=",
                "optionText": "TV"
            },
            {
                "url": "aHR0cHM6Ly92b29kYy5jb20vZW1iZWQvODU4MThiOTk5YzhiYTI4Njg0N2E4NTk4OWM4OTk4ODU4NTgyLmh0bWw=",
                "optionText": "TV"
            },
            {
                "url": "aHR0cHM6Ly92b29kYy5jb20vZW1iZWQvODU4MThiOTk5YzhiYTI4Njg0N2E4NTk4OWM4YTk4ODU4NTgzLmh0bWw=",
                "optionText": "TV"
            },
            {
                "url": "aHR0cHM6Ly92b29kYy5jb20vZW1iZWQvODU4MThiOTk5YzhiYTI4Njg0N2E4NTk4OWM4Yjk4ODU4NjdhLmh0bWw=",
                "optionText": "TV"
            }
        ]
    },
    {
        "time": "13:00",
        "tournament": "UEFA Champions League",
        "eventTitle": "Juventus vs. Borussia Dortmund",
        "streams": [
            {
                "url": "aHR0cHM6Ly92b29kYy5jb20vZW1iZWQvODU4MThiOTk5YzhiYTI4Njg0N2E4NTk4OWM4Yzk4ODU4NjdiLmh0bWw=",
                "optionText": "TV"
            },
            {
                "url": "aHR0cHM6Ly92b29kYy5jb20vZW1iZWQvODU4MThiOTk5YzhiYTI4Njg0N2E4NTk4OWM4ZDk4ODU4NjdjLmh0bWw=",
                "optionText": "TV"
            },
            {
                "url": "aHR0cHM6Ly92b29kYy5jb20vZW1iZWQvODU4MThiOTk5YzhiYTI4Njg0N2E4NTk4OWM4ZTk4ODU4NjdkLmh0bWw=",
                "optionText": "TV"
            },
            {
                "url": "aHR0cHM6Ly92b29kYy5jb20vZW1iZWQvODU4MThiOTk5YzhiYTI4Njg0N2E4NTk4OWM4Zjk4ODU4NjdlLmh0bWw=",
                "optionText": "TV"
            }
        ]
    },
    {
        "time": "13:00",
        "tournament": "UEFA Champions League",
        "eventTitle": "Real Madrid vs. Marseille",
        "streams": [
            {
                "url": "aHR0cHM6Ly92b29kYy5jb20vZW1iZWQvODU4MThiOTk5YzhiYTI4Njg0N2E4NTk4OWM5MDk4ODU4NjdmLmh0bWw=",
                "optionText": "TV"
            },
            {
                "url": "aHR0cHM6Ly92b29kYy5jb20vZW1iZWQvODU4MThiOTk5YzhiYTI4Njg0N2E4NTk4OWQ4Nzk4ODU4NjgwLmh0bWw=",
                "optionText": "TV"
            },
            {
                "url": "aHR0cHM6Ly92b29kYy5jb20vZW1iZWQvODU4MThiOTk5YzhiYTI4Njg0N2E4NTk4OWQ4ODk4ODU4NjgxLmh0bWw=",
                "optionText": "TV"
            },
            {
                "url": "aHR0cHM6Ly92b29kYy5jb20vZW1iZWQvODU4MThiOTk5YzhiYTI4Njg0N2E4NTk4OWQ4OTk4ODU4NjgyLmh0bWw=",
                "optionText": "TV"
            }
        ]
    },
    {
        "time": "13:00",
        "tournament": "UEFA Champions League",
        "eventTitle": "Tottenham vs. Villarreal",
        "streams": [
            {
                "url": "aHR0cHM6Ly92b29kYy5jb20vZW1iZWQvODU4MThiOTk5YzhiYTI4Njg0N2E4NTk4OWQ4YTk4ODU4NzdhLmh0bWw=",
                "optionText": "TV"
            },
            {
                "url": "aHR0cHM6Ly92b29kYy5jb20vZW1iZWQvODU4MThiOTk5YzhiYTI4Njg0N2E4NTk4OWQ4Yjk4ODU4NzdiLmh0bWw=",
                "optionText": "TV"
            },
            {
                "url": "aHR0cHM6Ly92b29kYy5jb20vZW1iZWQvODU4MThiOTk5YzhiYTI4Njg0N2E4NTk4OWQ4Yzk4ODU4NzdjLmh0bWw=",
                "optionText": "TV"
            }
        ]
    },
    {
        "time": "13:00",
        "tournament": "Bolivia",
        "eventTitle": "SA Bulo Bulo vs. Oriente Petrolero",
        "streams": [
            {
                "url": "aHR0cHM6Ly92b29kYy5jb20vZW1iZWQvODU4MThiOTk5YzhiYTI4Njg0N2E4NTk4OWQ4ZDk4ODU4NzdkLmh0bWw=",
                "optionText": "TV"
            }
        ]
    },
    {
        "time": "13:00",
        "tournament": "EFL Cup",
        "eventTitle": "Brentford vs. Aston Villa",
        "streams": [
            {
                "url": "aHR0cHM6Ly92b29kYy5jb20vZW1iZWQvODU4MThiOTk5YzhiYTI4Njg0N2E4NTk4OWQ4ZTk4ODU4NzdlLmh0bWw=",
                "optionText": "TV"
            }
        ]
    },
    {
        "time": "13:00",
        "tournament": "EFL Cup",
        "eventTitle": "Crystal Palace vs. Millwall",
        "streams": [
            {
                "url": "aHR0cHM6Ly92b29kYy5jb20vZW1iZWQvODU4MThiOTk5YzhiYTI4Njg0N2E4NTk4OWQ4Zjk4ODU4NzdmLmh0bWw=",
                "optionText": "TV"
            }
        ]
    },
    {
        "time": "14:00",
        "tournament": "Peru",
        "eventTitle": "AD Tarma vs. UTC Cajamarca",
        "streams": [
            {
                "url": "aHR0cHM6Ly92b29kYy5jb20vZW1iZWQvODU4MThiOTk5YzhjOWI4Yzg0N2E4NTk4OWQ5MDk4ODU4NzgxLmh0bWw=",
                "optionText": "TV"
            }
        ]
    },
    {
        "time": "14:30",
        "tournament": "Ecuador Serie B",
        "eventTitle": "Cumbaya vs. 22 de Julio",
        "streams": [
            {
                "url": "aHR0cHM6Ly92b29kYy5jb20vZW1iZWQvODU4MThiOTk5YzhjOWQ4YTg0N2E4NTk4OWU4ODk4ODU4NzgyLmh0bWw=",
                "optionText": "TV"
            }
        ]
    },
    {
        "time": "14:30",
        "tournament": "Ecuador Serie B",
        "eventTitle": "Gualaceo vs. Ind. Juniors",
        "streams": [
            {
                "url": "aHR0cHM6Ly92b29kYy5jb20vZW1iZWQvODU4MThiOTk5YzhjOWQ4YTg0N2E4NTk4OWU4OTk4ODU4NzgzLmh0bWw=",
                "optionText": "TV"
            }
        ]
    },
    {
        "time": "15:00",
        "tournament": "Colombia Primera B",
        "eventTitle": "Huila vs. Boca Juniors",
        "streams": [
            {
                "url": "aHR0cHM6Ly92b29kYy5jb20vZW1iZWQvODU4MThiOTk5YzhjOWY4ODg0N2E4NTk4OWU4YTk4ODU4ODdhLmh0bWw=",
                "optionText": "TV"
            }
        ]
    },
    {
        "time": "15:00",
        "tournament": "Guatemala",
        "eventTitle": "Coban Imperial vs. Xelaju",
        "streams": [
            {
                "url": "aHR0cHM6Ly92b29kYy5jb20vZW1iZWQvODU4MThiOTk5YzhjOWY4ODg0N2E4NTk4OWU4Yjk4ODU4ODdiLmh0bWw=",
                "optionText": "TV"
            }
        ]
    },
    {
        "time": "15:30",
        "tournament": "Copa do Brasil",
        "eventTitle": "Bahia W vs. Atletico-MG W",
        "streams": [
            {
                "url": "aHR0cHM6Ly92b29kYy5jb20vZW1iZWQvODU4MThiOTk5YzhjYTE4Njg0N2E4NTk4OWU4Yzk4ODU4ODdjLmh0bWw=",
                "optionText": "TV"
            }
        ]
    },
    {
        "time": "16:00",
        "tournament": "Copa Libertadores",
        "eventTitle": "Velez Sarsfield vs. Racing Club",
        "streams": [
            {
                "url": "aHR0cHM6Ly92b29kYy5jb20vZW1iZWQvODU4MThiOTk5YzhkOTk4NDg0N2E4NTk4OWU4ZDk4ODU4ODdkLmh0bWw=",
                "optionText": "TV"
            },
            {
                "url": "aHR0cHM6Ly92b29kYy5jb20vZW1iZWQvODU4MThiOTk5YzhkOTk4NDg0N2E4NTk4OWU4ZTk4ODU4ODdlLmh0bWw=",
                "optionText": "TV"
            },
            {
                "url": "aHR0cHM6Ly92b29kYy5jb20vZW1iZWQvODU4MThiOTk5YzhkOTk4NDg0N2E4NTk4OWU4Zjk4ODU4ODdmLmh0bWw=",
                "optionText": "TV"
            },
            {
                "url": "aHR0cHM6Ly92b29kYy5jb20vZW1iZWQvODU4MThiOTk5YzhkOTk4NDg0N2E4NTk4OWU5MDk4ODU4ODgwLmh0bWw=",
                "optionText": "TV"
            }
        ]
    },
    {
        "time": "16:30",
        "tournament": "Brazil Serie B",
        "eventTitle": "Atletico GO vs. Avai",
        "streams": [
            {
                "url": "aHR0cHM6Ly92b29kYy5jb20vZW1iZWQvODU4MThiOTk5YzhkOWE4Yzg0N2E4NTk4OWY4Nzk4ODU4ODgxLmh0bWw=",
                "optionText": "TV"
            }
        ]
    },
    {
        "time": "17:00",
        "tournament": "Colombia Primera A",
        "eventTitle": "America De Cali vs. Bucaramanga",
        "streams": [
            {
                "url": "aHR0cHM6Ly92b29kYy5jb20vZW1iZWQvODU4MThiOTk5YzhkOWM4YTg0N2E4NTk1OWM4Nzk4ODU4OTgwLmh0bWw=",
                "optionText": "TV"
            }
        ]
    },
    {
        "time": "17:30",
        "tournament": "MLS",
        "eventTitle": "Inter Miami vs. Seattle Sounders",
        "streams": [
            {
                "url": "aHR0cHM6Ly92b29kYy5jb20vZW1iZWQvODU4MThiOTk5YzhkOWU4ODg0N2E4NTk1OWM4Yzk4ODU4YTdhLmh0bWw=",
                "optionText": "TV"
            },
            {
                "url": "aHR0cHM6Ly92b29kYy5jb20vZW1iZWQvODU4MThiOTk5YzhkOWU4ODg0N2E4NTk1OWM4ZDk4ODU4YTdiLmh0bWw=",
                "optionText": "TV"
            }
        ]
    },
    {
        "time": "18:00",
        "tournament": "Bolivia",
        "eventTitle": "Real Oruro vs. Aurora",
        "streams": [
            {
                "url": "aHR0cHM6Ly92b29kYy5jb20vZW1iZWQvODU4MThiOTk5YzhkYTA4Njg0N2E4NTk1OWU4YTk4ODU4YjgyLmh0bWw=",
                "optionText": "TV"
            }
        ]
    },
    {
        "time": "18:00",
        "tournament": "CONCACAF Caribbean Cup",
        "eventTitle": "Central FC vs. Moca",
        "streams": [
            {
                "url": "aHR0cHM6Ly92b29kYy5jb20vZW1iZWQvODU4MThiOTk5YzhkYTA4Njg0N2E4NTk1OWU4Yjk4ODU4YjgzLmh0bWw=",
                "optionText": "TV"
            }
        ]
    },
    {
        "time": "18:00",
        "tournament": "CONCACAF W Champions Cup",
        "eventTitle": "Chorrillo W vs. Orlando Pride W",
        "streams": [
            {
                "url": "aHR0cHM6Ly92b29kYy5jb20vZW1iZWQvODU4MThiOTk5YzhkYTA4Njg0N2E4NTk1OWU4Yzk4ODU4YzdhLmh0bWw=",
                "optionText": "TV"
            },
            {
                "url": "aHR0cHM6Ly92b29kYy5jb20vZW1iZWQvODU4MThiOTk5YzhkYTA4Njg0N2E4NTk1OWU4ZDk4ODU4YzdiLmh0bWw=",
                "optionText": "TV"
            }
        ]
    },
    {
        "time": "18:00",
        "tournament": "NWSL",
        "eventTitle": "Seattle Reign W vs. Racing Louisville W",
        "streams": [
            {
                "url": "aHR0cHM6Ly92b29kYy5jb20vZW1iZWQvODU4MThiOTk5YzhkYTA4Njg0N2E4NTk1OWU4ZTk4ODU4YzdjLmh0bWw=",
                "optionText": "TV"
            }
        ]
    },
    {
        "time": "18:00",
        "tournament": "US Open Cup",
        "eventTitle": "Nashville SC vs. Philadelphia Union",
        "streams": [
            {
                "url": "aHR0cHM6Ly92b29kYy5jb20vZW1iZWQvODU4MThiOTk5YzhkYTA4Njg0N2E4NTk1OWU4Zjk4ODU4YzdkLmh0bWw=",
                "optionText": "TV"
            }
        ]
    },
    {
        "time": "18:30",
        "tournament": "Copa Sudamericana",
        "eventTitle": "Lanus vs. Fluminense",
        "streams": [
            {
                "url": "aHR0cHM6Ly92b29kYy5jb20vZW1iZWQvODU4MThiOTk5YzhkYTI4NDg0N2E4NTk1OWY4ODk4ODU4YzgxLmh0bWw=",
                "optionText": "TV"
            },
            {
                "url": "aHR0cHM6Ly92b29kYy5jb20vZW1iZWQvODU4MThiOTk5YzhkYTI4NDg0N2E4NTk1OWY4OTk4ODU4YzgyLmh0bWw=",
                "optionText": "TV"
            },
            {
                "url": "aHR0cHM6Ly92b29kYy5jb20vZW1iZWQvODU4MThiOTk5YzhkYTI4NDg0N2E4NTk1OWY4YTk4ODU4YzgzLmh0bWw=",
                "optionText": "TV"
            },
            {
                "url": "aHR0cHM6Ly92b29kYy5jb20vZW1iZWQvODU4MThiOTk5YzhkYTI4NDg0N2E4NTk1OWY4Yjk4ODU4ZDdhLmh0bWw=",
                "optionText": "TV"
            }
        ]
    },
    {
        "time": "18:35",
        "tournament": "Brazil Serie B",
        "eventTitle": "Chapecoense-SC vs. Athletico-PR",
        "streams": [
            {
                "url": "aHR0cHM6Ly92b29kYy5jb20vZW1iZWQvODU4MThiOTk5YzhkYTI4Nzg0N2E4NTk1OWY4Yzk4ODU4ZDdiLmh0bWw=",
                "optionText": "TV"
            }
        ]
    },
    {
        "time": "19:00",
        "tournament": "Guatemala",
        "eventTitle": "CSD Comunicaciones vs. Malacateco",
        "streams": [
            {
                "url": "aHR0cHM6Ly92b29kYy5jb20vZW1iZWQvODU4MThiOTk5YzhlOTk4Yzg0N2E4NTk1OWY4Zjk4ODU4ZDdlLmh0bWw=",
                "optionText": "TV"
            }
        ]
    },
    {
        "time": "19:10",
        "tournament": "Copa Colombia",
        "eventTitle": "Millonarios vs. Envigado",
        "streams": [
            {
                "url": "aHR0cHM6Ly92b29kYy5jb20vZW1iZWQvODU4MThiOTk5YzhlOWE4ODg0N2E4NTk1OWY5MDk4ODU4ZDdmLmh0bWw=",
                "optionText": "TV"
            }
        ]
    },
    {
        "time": "20:00",
        "tournament": "Canadian Championship",
        "eventTitle": "Vancouver Whitecaps vs. Forge",
        "streams": [
            {
                "url": "aHR0cHM6Ly92b29kYy5jb20vZW1iZWQvODU4MThiOTk5YzhlOWQ4ODg0N2E4NTk1YTA4YTk4ODY4NDdiLmh0bWw=",
                "optionText": "TV"
            }
        ]
    },
    {
        "time": "20:00",
        "tournament": "CONCACAF W Champions Cup",
        "eventTitle": "Vancouver Rise W vs. Gotham W",
        "streams": [
            {
                "url": "aHR0cHM6Ly92b29kYy5jb20vZW1iZWQvODU4MThiOTk5YzhlOWQ4ODg0N2E4NTk1YTA4Yjk4ODU4ZDgzLmh0bWw=",
                "optionText": "TV"
            },
            {
                "url": "aHR0cHM6Ly92b29kYy5jb20vZW1iZWQvODU4MThiOTk5YzhlOWQ4ODg0N2E4NTk1YTA4Yzk4ODY4NDdhLmh0bWw=",
                "optionText": "TV"
            }
        ]
    },
    {
        "time": "20:00",
        "tournament": "Costa Rica Primera Division",
        "eventTitle": "Alajuelense vs. San Carlos",
        "streams": [
            {
                "url": "aHR0cHM6Ly92b29kYy5jb20vZW1iZWQvODU4MThiOTk5YzhlOWQ4ODg0N2E4NTk1YTA4ZDk4ODY4NDdjLmh0bWw=",
                "optionText": "TV"
            }
        ]
    }
]